frost_typing/__init__.py
frost_typing/frost_typing.cp313-win_amd64.pyd
frost_typing/frost_typing.pyi
frost_typing-2.0.0.dist-info/licenses/LICENSE
frost_typing-2.0.0.dist-info/METADATA
frost_typing-2.0.0.dist-info/WHEEL
frost_typing-2.0.0.dist-info/top_level.txt
frost_typing-2.0.0.dist-info/RECORD
