Metadata-Version: 2.4
Name: frost_typing
Version: 2.0.0
Summary: Fast and efficient Python typing and validation library
Author-email: Sergey Galchenkov <frost_typing_python@mail.ru>
License-Expression: Apache-2.0
Project-URL: Homepage, https://gitflic.ru/project/frostic/frost_typing
Project-URL: Documentation, https://gitflic.ru/project/frostic/frost_typing
Project-URL: Source, https://gitflic.ru/project/frostic/frost_typing
Keywords: typing,validation,dataclass,fast,model,json,type-checking,performance,runtime,schema,datetime
Classifier: Development Status :: 5 - Production/Stable
Classifier: Programming Language :: Python
Classifier: Programming Language :: Python :: Implementation :: CPython
Classifier: Programming Language :: Python :: Implementation :: PyPy
Classifier: Programming Language :: Python :: 3
Classifier: Programming Language :: Python :: 3 :: Only
Classifier: Programming Language :: Python :: 3.9
Classifier: Programming Language :: Python :: 3.10
Classifier: Programming Language :: Python :: 3.11
Classifier: Programming Language :: Python :: 3.12
Classifier: Programming Language :: Python :: 3.13
Classifier: Programming Language :: Python :: 3.14
Classifier: Intended Audience :: Developers
Classifier: Intended Audience :: Information Technology
Classifier: Operating System :: OS Independent
Classifier: Topic :: Software Development :: Libraries :: Python Modules
Classifier: Topic :: Internet
Requires-Python: >=3.9
License-File: LICENSE
Dynamic: license-file
